harbor_cli/__about__.py
harbor_cli/__init__.py
harbor_cli/__main__.py
harbor_cli/app.py
harbor_cli/config.py
harbor_cli/deprecation.py
harbor_cli/dirs.py
harbor_cli/exceptions.py
harbor_cli/format.py
harbor_cli/logs.py
harbor_cli/main.py
harbor_cli/models.py
harbor_cli/option.py
harbor_cli/state.py
harbor_cli/types.py
harbor_cli/commands/__init__.py
harbor_cli/commands/help.py
harbor_cli/commands/api/__init__.py
harbor_cli/commands/api/artifact.py
harbor_cli/commands/api/auditlog.py
harbor_cli/commands/api/cve_allowlist.py
harbor_cli/commands/api/gc.py
harbor_cli/commands/api/harbor_config.py
harbor_cli/commands/api/ldap.py
harbor_cli/commands/api/project.py
harbor_cli/commands/api/quotas.py
harbor_cli/commands/api/registry.py
harbor_cli/commands/api/replication.py
harbor_cli/commands/api/repository.py
harbor_cli/commands/api/retention.py
harbor_cli/commands/api/scan.py
harbor_cli/commands/api/scanall.py
harbor_cli/commands/api/scanner.py
harbor_cli/commands/api/search.py
harbor_cli/commands/api/system.py
harbor_cli/commands/api/user.py
harbor_cli/commands/api/usergroup.py
harbor_cli/commands/api/webhook.py
harbor_cli/commands/cli/__init__.py
harbor_cli/commands/cli/cache.py
harbor_cli/commands/cli/cli_config.py
harbor_cli/commands/cli/find.py
harbor_cli/commands/cli/init.py
harbor_cli/commands/cli/repl.py
harbor_cli/commands/cli/sample_config.py
harbor_cli/commands/cli/self.py
harbor_cli/commands/cli/tui.py
harbor_cli/harbor/__init__.py
harbor_cli/harbor/artifact.py
harbor_cli/harbor/common.py
harbor_cli/output/__init__.py
harbor_cli/output/console.py
harbor_cli/output/prompts.py
harbor_cli/output/render.py
harbor_cli/output/formatting/__init__.py
harbor_cli/output/formatting/builtin.py
harbor_cli/output/formatting/bytes.py
harbor_cli/output/formatting/constants.py
harbor_cli/output/formatting/dates.py
harbor_cli/output/formatting/harbor.py
harbor_cli/output/formatting/path.py
harbor_cli/output/table/__init__.py
harbor_cli/output/table/_utils.py
harbor_cli-0.2.2.dist-info/METADATA
harbor_cli-0.2.2.dist-info/WHEEL
harbor_cli-0.2.2.dist-info/entry_points.txt
harbor_cli-0.2.2.dist-info/licenses/LICENSE.txt
harbor_cli-0.2.2.dist-info/RECORD
