Metadata-Version: 2.1
Name: harbor-cli
Version: 0.2.2
Project-URL: Source, https://github.com/unioslo/harbor-cli
Project-URL: Documentation, https://unioslo.github.io/harbor-cli/
Project-URL: Changelog, https://github.com/unioslo/harbor-cli/blob/main/CHANGELOG.md
Project-URL: Issues, https://github.com/unioslo/harbor-cli/issues
Author-email: pederhan <pederhan@uio.no>
License-Expression: MIT
License-File: LICENSE.txt
Classifier: Development Status :: 4 - Beta
Classifier: Intended Audience :: System Administrators
Classifier: License :: OSI Approved :: MIT License
Classifier: Natural Language :: English
Classifier: Operating System :: OS Independent
Classifier: Programming Language :: Python
Classifier: Programming Language :: Python :: 3.8
Classifier: Programming Language :: Python :: 3.9
Classifier: Programming Language :: Python :: 3.10
Classifier: Programming Language :: Python :: 3.11
Classifier: Programming Language :: Python :: 3.12
Classifier: Programming Language :: Python :: Implementation :: CPython
Classifier: Topic :: Internet
Classifier: Topic :: System :: Systems Administration
Classifier: Topic :: Utilities
Classifier: Typing :: Typed
Requires-Python: >=3.8
Requires-Dist: click-repl==0.2.0
Requires-Dist: fuzzywuzzy>=0.18.0
Requires-Dist: harborapi>=0.23.4
Requires-Dist: httpx[socks]>=0.26.0
Requires-Dist: keyring>=24.2.0
Requires-Dist: platformdirs>=2.5.4
Requires-Dist: pydantic>=2.4.0
Requires-Dist: python-levenshtein>=0.20.9
Requires-Dist: rich>=12.6.0
Requires-Dist: strenum>=0.4.15
Requires-Dist: tomli-w>=1.0.0
Requires-Dist: tomli>=2.0.1
Requires-Dist: trogon>=0.5.0
Requires-Dist: typer==0.9.0
